pytest_human/__init__.py
pytest_human/_code_style.py
pytest_human/_flags.py
pytest_human/_hooks.py
pytest_human/exceptions.py
pytest_human/fixtures.py
pytest_human/html_format.py
pytest_human/html_handler.py
pytest_human/human.py
pytest_human/log.py
pytest_human/plugin.py
pytest_human/repo.py
pytest_human/tracing.py
pytest_human/templates/block_end.html
pytest_human/templates/block_start.html
pytest_human/templates/footer.html
pytest_human/templates/header.html
pytest_human/templates/record.html
pytest_human/templates/script.js
pytest_human/templates/styles.css
pytest_human-1.2.0.dist-info/licenses/LICENSE
pytest_human-1.2.0.dist-info/METADATA
pytest_human-1.2.0.dist-info/WHEEL
pytest_human-1.2.0.dist-info/entry_points.txt
pytest_human-1.2.0.dist-info/top_level.txt
pytest_human-1.2.0.dist-info/RECORD
