Metadata-Version: 2.4
Name: pytest-human
Version: 1.2.0
Summary: A beautiful nested pytest HTML test report
Author-email: Dan Ilan <dan.ilan@q.ai>
Maintainer-email: Dan Ilan <dan.ilan@q.ai>
License:                                  Apache License
Project-URL: Changelog, https://github.com/Q-cue-ai/pytest-human/releases
Project-URL: Issues, https://github.com/Q-cue-ai/pytest-human/issues
Project-URL: Repository, https://github.com/Q-cue-ai/pytest-human
Keywords: debug,html,human,log,logging,pytest,report,testing,automation,e2e,robot
Classifier: Development Status :: 4 - Beta
Classifier: Framework :: Pytest
Classifier: Intended Audience :: Developers
Classifier: License :: OSI Approved :: Apache Software License
Classifier: Operating System :: OS Independent
Classifier: Programming Language :: Python
Classifier: Programming Language :: Python :: 3 :: Only
Classifier: Programming Language :: Python :: 3.10
Classifier: Programming Language :: Python :: 3.11
Classifier: Programming Language :: Python :: 3.12
Classifier: Programming Language :: Python :: 3.13
Classifier: Programming Language :: Python :: 3.14
Classifier: Programming Language :: Python :: Implementation :: CPython
Classifier: Programming Language :: Python :: Implementation :: PyPy
Classifier: Topic :: Software Development :: Quality Assurance
Classifier: Topic :: Software Development :: Testing
Requires-Python: >=3.10
License-File: LICENSE
Requires-Dist: gitpython==3.*
Requires-Dist: jinja2>=3.1
Requires-Dist: pytest>=8
Requires-Dist: rich==14.*
Dynamic: license-file
